tadmap/__init__.py
tadmap/tad_signature.py
tadmap/tadmap_base_config.py
tadmap/tadmap_utils.py
tadmap/data/__init__.py
tadmap/data/_tadmap_data.py
tadmap-0.1.2.dist-info/LICENSE
tadmap-0.1.2.dist-info/METADATA
tadmap-0.1.2.dist-info/WHEEL
tadmap-0.1.2.dist-info/top_level.txt
tadmap-0.1.2.dist-info/RECORD
