Metadata-Version: 2.1
Name: tadmap
Version: 0.1.2
Summary: Consensus layout of topologically associating domains (TADs) and utilities for RNA-seq analysis
Home-page: http://github.com/rs239/tadmap
Author: Rohit Singh
Author-email: rsingh@alum.mit.edu
License: MIT
Platform: UNKNOWN
License-File: LICENSE
Requires-Dist: numpy
Requires-Dist: scipy
Requires-Dist: pandas
Requires-Dist: sklearn
Requires-Dist: tqdm
Requires-Dist: scanpy
